odoo/addons/queue_job_web_notify/README.rst
odoo/addons/queue_job_web_notify/__init__.py
odoo/addons/queue_job_web_notify/__manifest__.py
odoo/addons/queue_job_web_notify/i18n/fr.po
odoo/addons/queue_job_web_notify/i18n/queue_job_web_notify.pot
odoo/addons/queue_job_web_notify/models/__init__.py
odoo/addons/queue_job_web_notify/models/queue_job.py
odoo/addons/queue_job_web_notify/models/queue_job_function.py
odoo/addons/queue_job_web_notify/readme/CONFIGURE.md
odoo/addons/queue_job_web_notify/readme/CONTEXT.md
odoo/addons/queue_job_web_notify/readme/CONTRIBUTORS.md
odoo/addons/queue_job_web_notify/readme/DESCRIPTION.md
odoo/addons/queue_job_web_notify/readme/ROADMAP.md
odoo/addons/queue_job_web_notify/readme/USAGE.md
odoo/addons/queue_job_web_notify/static/description/icon.png
odoo/addons/queue_job_web_notify/static/description/index.html
odoo/addons/queue_job_web_notify/views/queue_job_function.xml
odoo13_addon_queue_job_web_notify-13.0.1.0.1.dev2.dist-info/METADATA
odoo13_addon_queue_job_web_notify-13.0.1.0.1.dev2.dist-info/WHEEL
odoo13_addon_queue_job_web_notify-13.0.1.0.1.dev2.dist-info/top_level.txt
odoo13_addon_queue_job_web_notify-13.0.1.0.1.dev2.dist-info/RECORD
