Metadata-Version: 2.1
Name: odoo13-addon-queue-job-web-notify
Version: 13.0.1.0.1.dev2
Summary: This module allows to display a notification to the related user of a failed job. It uses the web_notify notification feature.
Home-page: https://github.com/OCA/queue
Author: ACSONE SA/NV,Odoo Community Association (OCA)
Author-email: support@odoo-community.org
License: AGPL-3
Platform: UNKNOWN
Classifier: Programming Language :: Python
Classifier: Framework :: Odoo
Classifier: Framework :: Odoo :: 13.0
Classifier: License :: OSI Approved :: GNU Affero General Public License v3
Requires-Python: >=3.5
Requires-Dist: odoo13-addon-queue-job
Requires-Dist: odoo13-addon-web-notify
Requires-Dist: odoo <13.1dev,>=13.0a
